xRBM-0.1.1.dist-info/DESCRIPTION.rst
xRBM-0.1.1.dist-info/METADATA
xRBM-0.1.1.dist-info/RECORD
xRBM-0.1.1.dist-info/WHEEL
xRBM-0.1.1.dist-info/metadata.json
xRBM-0.1.1.dist-info/top_level.txt
xrbm/__init__.py
xrbm/losses/__init__.py
xrbm/losses/losses.py
xrbm/models/__init__.py
xrbm/models/_crbm.py
xrbm/models/abstract_model.py
xrbm/models/crbm.py
xrbm/models/rbm.py
xrbm/train/__init__.py
xrbm/train/cdk.py
xrbm/train/cdlearner.py
xrbm/utils/__init__.py
xrbm/utils/costs.py
xrbm/utils/nnviz.py
xrbm/utils/tfutils.py
xrbm/utils/vizutils.py
